{
	"schemaVersion": 1,
	"id": "youtube-chat",
	"version": "${version}",
	"name": "YouTube Chat",
	"description": "This is an example description! Tell everyone what your mod is about!",
	"authors": [
		"Me!"
	],
	"contact": {
		"homepage": "https://fabricmc.net/",
		"sources": "https://github.com/FabricMC/fabric-example-mod"
	},
	"license": "CC0-1.0",
	"icon": "assets/youtube-chat/icon.png",
	"environment": "*",
	"entrypoints": {
		"main": [
			{
				"value": "ally.ytchat.YouTubeChat",
				"adapter": "kotlin"
			}
		],
		"client": [
			{
				"value": "ally.ytchat.YouTubeChatClient",
				"adapter": "kotlin"
			}
		]
	},
	"depends": {
		"fabricloader": ">=0.15.9",
		"minecraft": "~1.20.4",
		"java": ">=17",
		"fabric-api": "*",
		"fabric-language-kotlin": ">=1.9.23"
	},
	"suggests": {
		"another-mod": "*"
	}
}